CHANGES.txt
MANIFEST.in
setup.cfg
setup.py
justified_demo/__init__.py
justified_demo/__main__.py
justified_demo/actions.py
justified_demo/components.py
justified_demo/constants.py
justified_demo/reducers.py
justified_demo.egg-info/PKG-INFO
justified_demo.egg-info/SOURCES.txt
justified_demo.egg-info/dependency_links.txt
justified_demo.egg-info/requires.txt
justified_demo.egg-info/top_level.txt