Metadata-Version: 1.0
Name: justified-demo
Version: 0.1.1
Summary: Text-justification demo
Home-page: http://github.com/benjamin9999/justified_demo/
Author: Benjamin Yates
Author-email: benjamin@rqdq.com
License: MIT
Platform: UNKNOWN
